pygenia/__init__.py
pygenia/affective_agent.py
pygenia/empathic_agent.py
pygenia/empathic_environment.py
pygenia/environment.py
pygenia/lexer.py
pygenia/parser.py
pygenia/stdlib.py
pygenia/utils.py
pygenia-0.1.0.dist-info/AUTHORS.rst
pygenia-0.1.0.dist-info/LICENSE
pygenia-0.1.0.dist-info/METADATA
pygenia-0.1.0.dist-info/WHEEL
pygenia-0.1.0.dist-info/top_level.txt
pygenia-0.1.0.dist-info/RECORD
