Metadata-Version: 2.1
Name: pygenia
Version: 0.1.0
Summary: Emotional agents in AgentSpeak
Home-page: https://github.com/gti-ia/pygenia
Author: Joaquin Taverner
Author-email: joataap@dsic.upv.es
License: MIT license
Keywords: pygenia
Classifier: Development Status :: 2 - Pre-Alpha
Classifier: Intended Audience :: Developers
Classifier: License :: OSI Approved :: MIT License
Classifier: Natural Language :: English
Classifier: Programming Language :: Python :: 3
Classifier: Programming Language :: Python :: 3.8
Classifier: Programming Language :: Python :: 3.9
Classifier: Programming Language :: Python :: 3.10
Requires-Python: >=3.8
License-File: LICENSE
License-File: AUTHORS.rst
Requires-Dist: agentspeak ==0.2.2
Requires-Dist: colorama ==0.4.6
Requires-Dist: numpy ==1.26.3
Requires-Dist: pandas ==2.2.1
Requires-Dist: scipy ==1.12.0
